acheeve/__init__.py
acheeve/descriptiveness.py
acheeve/tests/__init__.py
acheeve/tests/prepare_data.py
acheeve/tests/test_descriptiveness.py
acheeve-0.0.3.dist-info/LICENSE
acheeve-0.0.3.dist-info/METADATA
acheeve-0.0.3.dist-info/WHEEL
acheeve-0.0.3.dist-info/top_level.txt
acheeve-0.0.3.dist-info/RECORD
