Metadata-Version: 2.1
Name: acheeve
Version: 0.0.3
Summary: Package coodinating multiple chembees
Home-page: https://codeberg.org/sail.black/acheeve.git
Author: Julian M. Kleber
Author-email: julian.kleber@sail.black
Classifier: Programming Language :: Python :: 3
Classifier: License :: OSI Approved :: GNU Affero General Public License v3 or later (AGPLv3+)
Classifier: Operating System :: OS Independent
Requires-Python: >=3.9
License-File: LICENSE
Requires-Dist: pandas
Requires-Dist: scikit-learn
Requires-Dist: rdkit
Requires-Dist: mordred
Requires-Dist: matplotlib
Requires-Dist: progressbar
Requires-Dist: tqdm
Requires-Dist: scipy
Requires-Dist: numpy
Requires-Dist: pyADAqsar
Requires-Dist: radiant-rdkit
